unstable_baselines3/__init__.py
unstable_baselines3/a2c/A2C.py
unstable_baselines3/a2c/__init__.py
unstable_baselines3/common/__init__.py
unstable_baselines3/common/aec_alg.py
unstable_baselines3/common/auto_multi_alg.py
unstable_baselines3/common/common.py
unstable_baselines3/common/multi_agent_alg.py
unstable_baselines3/common/off_policy.py
unstable_baselines3/common/on_policy.py
unstable_baselines3/common/parallel_alg.py
unstable_baselines3/ddpg/DDPG.py
unstable_baselines3/ddpg/__init__.py
unstable_baselines3/dqn/DQN.py
unstable_baselines3/dqn/__init__.py
unstable_baselines3/ppo/PPO.py
unstable_baselines3/ppo/__init__.py
unstable_baselines3/sac/SAC.py
unstable_baselines3/sac/__init__.py
unstable_baselines3/td3/TD3.py
unstable_baselines3/td3/__init__.py
unstable_baselines3/utils/__init__.py
unstable_baselines3/utils/dict_keys.py
unstable_baselines3-0.0.3100069.dist-info/LICENSE
unstable_baselines3-0.0.3100069.dist-info/METADATA
unstable_baselines3-0.0.3100069.dist-info/WHEEL
unstable_baselines3-0.0.3100069.dist-info/top_level.txt
unstable_baselines3-0.0.3100069.dist-info/RECORD
